combine_signatures/__init__.py
combine_signatures/combine_signatures.py
combine_signatures-0.1.0.dist-info/LICENSE
combine_signatures-0.1.0.dist-info/METADATA
combine_signatures-0.1.0.dist-info/WHEEL
combine_signatures-0.1.0.dist-info/top_level.txt
combine_signatures-0.1.0.dist-info/RECORD
